{"cameraMode":{"drawMode":0,"name":"Shaded","section":"Shading Mode"},"sceneLighting":false,"audioPlay":false,"sceneViewState":{"showFog":true,"showMaterialUpdate":false,"showSkybox":false,"showFlares":true,"showImageEffects":true,"showParticleSystems":true,"showVisualEffectGraphs":true,"m_FxEnabled":true},"in2DMode":false,"pivot":{"x":356.97998046875,"y":162.836669921875,"z":-0.07000000029802323},"rotation":{"x":-0.1154354140162468,"y":-0.7644663453102112,"z":0.14260728657245637,"w":-0.6181508898735046},"size":0.8929822444915772,"orthographic":true}